netizen/__init__.py
netizen/http_header.py
netizen/http_response.py
netizen-0.0.1.dist-info/LICENSE
netizen-0.0.1.dist-info/METADATA
netizen-0.0.1.dist-info/WHEEL
netizen-0.0.1.dist-info/top_level.txt
netizen-0.0.1.dist-info/RECORD
