Metadata-Version: 2.1
Name: netizen
Version: 0.0.1
Summary: Netizen is a minimalist HTTP client with a symmetrical interface between async and sync modes.
Author-email: Anggit Arfanto <contact@anggit.com>
License: MIT License
Project-URL: Homepage, https://github.com/nggit/netizen
Project-URL: Source, https://github.com/nggit/netizen
Project-URL: Funding, https://github.com/sponsors/nggit
Classifier: Development Status :: 4 - Beta
Classifier: Intended Audience :: Developers
Classifier: License :: OSI Approved :: MIT License
Classifier: Operating System :: OS Independent
Classifier: Topic :: Internet :: WWW/HTTP
Classifier: Topic :: Software Development :: Libraries
Classifier: Framework :: AsyncIO
Requires-Python: >=3.7
License-File: LICENSE
